hw1lib/__init__.py
hw1lib/curry_class.py
hw1lib-0.1.0.dist-info/METADATA
hw1lib-0.1.0.dist-info/WHEEL
hw1lib-0.1.0.dist-info/top_level.txt
hw1lib-0.1.0.dist-info/RECORD
